refinda/__init__.py
refinda/__main__.py
refinda/dataprovider/__init__.py
refinda/datasets/__init__.py
refinda/datasets/datasets.py
refinda/datasets/downloader.py
refinda/datasets/french49.py
refinda/preprocessors/__init__.py
refinda/preprocessors/helper.py
refinda/preprocessors/indicators.py
refinda-1.0.2.dist-info/LICENSE
refinda-1.0.2.dist-info/METADATA
refinda-1.0.2.dist-info/WHEEL
refinda-1.0.2.dist-info/entry_points.txt
refinda-1.0.2.dist-info/top_level.txt
refinda-1.0.2.dist-info/RECORD
