Metadata-Version: 2.1
Name: refinda
Version: 1.0.2
Summary: Reproducible Finance Data: Standardized datasets for finance research tasks.
Home-page: https://github.com/kruthof/refinda
Author: Garvin Kruthof
Author-email: 
License: MIT License        
Project-URL: Homepage, https://kruthof.github.io/projects/refinda/
Keywords: finance,machine learning,trading,portfolio management
Classifier: License :: OSI Approved :: MIT License
Classifier: Programming Language :: Python
Classifier: Programming Language :: Python :: 3
Requires-Python: >=3.7
License-File: LICENSE
Requires-Dist: numpy (>=1.21.*)
Requires-Dist: pandas (>=1.2.*)
Requires-Dist: wrds (==3.1.1)
Requires-Dist: tqdm (==4.62.3)
Requires-Dist: ta (==0.9.0)
Provides-Extra: dev
Requires-Dist: black ; extra == 'dev'
Requires-Dist: bumpver ; extra == 'dev'
Requires-Dist: isort ; extra == 'dev'
Requires-Dist: pip-tools ; extra == 'dev'
Requires-Dist: pytest ; extra == 'dev'
